ahttpdc/__init__.py
ahttpdc/read/__init__.py
ahttpdc/read/daemon.py
ahttpdc/read/database_interface.py
ahttpdc/read/fetch/__init__.py
ahttpdc/read/fetch/fetcher.py
ahttpdc/read/query/__init__.py
ahttpdc/read/query/interface.py
ahttpdc/read/query/parse/data.py
ahttpdc/read/store/__init__.py
ahttpdc/read/store/collector.py
ahttpdc/read/store/parse/__init__.py
ahttpdc/read/store/parse/parser.py
async_httpd_data_collector-2.0.2.dist-info/METADATA
async_httpd_data_collector-2.0.2.dist-info/WHEEL
async_httpd_data_collector-2.0.2.dist-info/licenses/LICENSE
async_httpd_data_collector-2.0.2.dist-info/RECORD
