Metadata-Version: 2.3
Name: async-httpd-data-collector
Version: 2.0.2
Summary: Gateway facilitating asyncronous communication between sensory data-emitting devices, InfluxDB and the user.
Project-URL: Repository, https://github.com/straightchlorine/async-httpd-data-collector
Project-URL: Issues, https://github.com/straightchlorine/async-httpd-data-collector/issues
Author-email: Piotr Krzysztof Lis <piotrlis555@gmail.com>
License:                     GNU GENERAL PUBLIC LICENSE
License-File: LICENSE
Keywords: arduino,async,collector,data,http,influxdb,json,nodemcu,sensors
Classifier: Development Status :: 3 - Alpha
Classifier: Intended Audience :: Developers
Classifier: Programming Language :: Python :: 3
Classifier: Topic :: Database
Classifier: Topic :: Software Development :: Libraries :: Python Modules
Requires-Python: >=3.8
Requires-Dist: aiocsv
Requires-Dist: aiohttp
Requires-Dist: aiosignal
Requires-Dist: attrs
Requires-Dist: certifi
Requires-Dist: frozenlist
Requires-Dist: idna
Requires-Dist: influxdb-client[async]
Requires-Dist: multidict
Requires-Dist: numpy
Requires-Dist: pandas
Requires-Dist: python-dateutil
Requires-Dist: pytz
Requires-Dist: reactivex
Requires-Dist: setuptools
Requires-Dist: six
Requires-Dist: typing-extensions
Requires-Dist: tzdata
Requires-Dist: urllib3
Requires-Dist: yarl
Provides-Extra: test
Requires-Dist: blinker; extra == 'test'
Requires-Dist: charset-normalizer; extra == 'test'
Requires-Dist: click; extra == 'test'
Requires-Dist: dash; extra == 'test'
Requires-Dist: dash-core-components; extra == 'test'
Requires-Dist: dash-html-components; extra == 'test'
Requires-Dist: dash-table; extra == 'test'
Requires-Dist: flask; extra == 'test'
Requires-Dist: importlib-metadata; extra == 'test'
Requires-Dist: iniconfig; extra == 'test'
Requires-Dist: itsdangerous; extra == 'test'
Requires-Dist: jinja2; extra == 'test'
Requires-Dist: markupsafe; extra == 'test'
Requires-Dist: nest-asyncio; extra == 'test'
Requires-Dist: packaging; extra == 'test'
Requires-Dist: plotly; extra == 'test'
Requires-Dist: pluggy; extra == 'test'
Requires-Dist: pytest; extra == 'test'
Requires-Dist: pytest-asyncio; extra == 'test'
Requires-Dist: requests; extra == 'test'
Requires-Dist: retrying; extra == 'test'
Requires-Dist: tenacity; extra == 'test'
Requires-Dist: werkzeug; extra == 'test'
Requires-Dist: zipp; extra == 'test'
